fw_hpc_client/__init__.py
fw_hpc_client/assets/cast.yml
fw_hpc_client/assets/credentials.sh
fw_hpc_client/assets/start-cast.sh
fw_hpc_client/cast.py
fw_hpc_client/cluster/__init__.py
fw_hpc_client/cluster/base.py
fw_hpc_client/cluster/common.py
fw_hpc_client/cluster/lsf.py
fw_hpc_client/cluster/sge.py
fw_hpc_client/cluster/slurm.py
fw_hpc_client/util/__init__.py
fw_hpc_client/util/basic_setup.py
fw_hpc_client/util/defn.py
fw_hpc_client/util/frame.py
fw_hpc_client/util/net.py
fw_hpc_client-2.1.0.dist-info/LICENSE
fw_hpc_client-2.1.0.dist-info/METADATA
fw_hpc_client-2.1.0.dist-info/WHEEL
fw_hpc_client-2.1.0.dist-info/entry_points.txt
fw_hpc_client-2.1.0.dist-info/RECORD
